[{"model": "order.containerpricing", "pk": 7, "fields": {"no_of_floors": "1 Story", "variant": "1 Wide", "square_feet": "290", "price": "75000.00", "price21": "65000.00", "model_image": "/static/users/imgs/coming_soon.png", "model_name": null, "model_link": ""}}, {"model": "order.containerpricing", "pk": 8, "fields": {"no_of_floors": "1 Story", "variant": "2 Wide", "square_feet": "633", "price": "103000.00", "price21": "140000.00", "model_image": "/static/users/interior_exterior/front.png", "model_name": null, "model_link": "1S-2W"}}, {"model": "order.containerpricing", "pk": 9, "fields": {"no_of_floors": "1 Story", "variant": "3 Wide", "square_feet": "870", "price": "150000.00", "price21": "140000.00", "model_image": "/static/users/imgs/coming_soon.png", "model_name": null, "model_link": ""}}, {"model": "order.containerpricing", "pk": 10, "fields": {"no_of_floors": "2 Story", "variant": "1 Wide", "square_feet": "580", "price": "100000.00", "price21": "90000.00", "model_image": "/static/users/imgs/coming_soon.png", "model_name": null, "model_link": ""}}, {"model": "order.containerpricing", "pk": 11, "fields": {"no_of_floors": "2 Story", "variant": "2 Wide", "square_feet": "1267", "price": "200000.00", "price21": "200000.00", "model_image": "/static/users/imgs/coming_soon.png", "model_name": null, "model_link": ""}}, {"model": "order.containerpricing", "pk": 12, "fields": {"no_of_floors": "2 Story", "variant": "3 Wide", "square_feet": "1740", "price": "310000.00", "price21": "300000.00", "model_image": "/static/users/imgs/2S3W/2 story 3 wide_front.jpg", "model_name": null, "model_link": "2S-3W"}}, {"model": "order.containerpricing", "pk": 13, "fields": {"no_of_floors": "3 story", "variant": "1 Wide", "square_feet": "870", "price": "175000.00", "price21": "165000.00", "model_image": "/static/users/imgs/coming_soon.png", "model_name": null, "model_link": ""}}, {"model": "order.containerpricing", "pk": 14, "fields": {"no_of_floors": "3 Story", "variant": "2 Wide", "square_feet": "1,900", "price": "329000.00", "price21": "319000.00", "model_image": "/static/users/new_custom/img/Bedroom-FINAL.jpg", "model_name": null, "model_link": "3S-2W"}}, {"model": "order.containerpricing", "pk": 15, "fields": {"no_of_floors": "3 Story", "variant": "3 Wide", "square_feet": "2,610", "price": "470000.00", "price21": "460000.00", "model_image": "/static/users/imgs/coming_soon.png", "model_name": null, "model_link": null}}]